distributed_sampling/__init__.py
distributed_sampling/api.py
distributed_sampling/registry.py
distributed_sampling/samplers/__init__.py
distributed_sampling/samplers/base.py
distributed_sampling/samplers/bfs.py
distributed_sampling/samplers/dfs.py
distributed_sampling/samplers/forest_fire.py
distributed_sampling/samplers/mdrw.py
distributed_sampling/samplers/mhrw.py
distributed_sampling/samplers/mirw.py
distributed_sampling/samplers/nuvsn.py
distributed_sampling/samplers/random_edge.py
distributed_sampling/samplers/random_node.py
distributed_sampling/samplers/random_walk.py
distributed_sampling/samplers/rwe.py
distributed_sampling/samplers/snowball.py
distributed_sampling/samplers/topk.py
distributed_sampling/samplers/uvsn.py
graph_distributed_sampling-1.0.0.dist-info/licenses/LICENSE
graph_distributed_sampling-1.0.0.dist-info/METADATA
graph_distributed_sampling-1.0.0.dist-info/WHEEL
graph_distributed_sampling-1.0.0.dist-info/entry_points.txt
graph_distributed_sampling-1.0.0.dist-info/top_level.txt
graph_distributed_sampling-1.0.0.dist-info/RECORD
