Metadata-Version: 2.4
Name: graph-distributed-sampling
Version: 1.0.0
Summary: Extensible distributed graph sampling library for Spark GraphFrames
Author-email: Joze Rozanec <jmrozanec@gmail.com>
License: Apache License
Project-URL: Homepage, https://github.com/graph-massivizer/distributed-sampling-library
Project-URL: Issues, https://github.com/graph-massivizer/distributed-sampling-library/issues
Keywords: spark,graphframes,graph,sampling,distributed
Classifier: Development Status :: 5 - Production/Stable
Classifier: Intended Audience :: Developers
Classifier: License :: OSI Approved :: Apache Software License
Classifier: Programming Language :: Python
Classifier: Programming Language :: Python :: 3
Classifier: Programming Language :: Python :: 3 :: Only
Classifier: Programming Language :: Python :: 3.9
Classifier: Programming Language :: Python :: 3.10
Classifier: Programming Language :: Python :: 3.11
Classifier: Programming Language :: Python :: 3.12
Classifier: Topic :: Software Development :: Libraries
Requires-Python: >=3.9
License-File: LICENSE
Provides-Extra: dev
Requires-Dist: pytest>=7.0; extra == "dev"
Requires-Dist: pytest-cov>=4.0; extra == "dev"
Requires-Dist: mypy>=1.7; extra == "dev"
Requires-Dist: ruff>=0.6; extra == "dev"
Dynamic: license-file
